Workbook

Sheet 📋 Index
A1: ROOTER GROWTH STRATEGY — COMBINED ASSIGNMENT MODEL
A3: Sheet | B3: Covers | C3: Question | D3: Parts
A4: Q1 — Inputs | B4: Given numbers + Lever assumptions | C4: Q1 | D4: Setup
A5: Q1 — BaseCase | B5: Monthly & Annual P&L baseline | C5: Q1 | D5: Part A
A6: Q1 — Scenarios | B6: Lever 1 (Frequency) vs Lever 2 (AOV) | C6: Q1 | D6: Part A + B
A7: Q1 — StressTest | B7: Sensitivity tables + critical assumption | C7: Q1 | D7: Part C
A8: Q2 — Inputs | B8: Tournament params + segment assumptions | C8: Q2 | D8: Setup
A9: Q2 — Diagnosis | B9: Negative feedback loop + psychology | C9: Q2 | D9: Part A
A10: Q2 — RewardFramework | B10: Budget allocation across 5 tiers | C10: Q2 | D10: Part B
A11: Q2 — NonMonetary | B11: ₹0 reward mechanisms (specific) | C11: Q2 | D11: Part C
A12: Q2 — StressTest | B12: Same-winner repeat scenario + fixes | C12: Q2 | D12: Part D
A13: AI Prompt Log | B13: All prompts + tools used for this model | C13: Both | D13: Disclosure
A15: Color Legend:
A16: 🔵 Blue text = Hardcoded inputs (you can change these)
A17: ⬛ Black text = Formula / calculated values
A18: 🟡 Yellow fill = Key assumptions requiring attention
A19: 🟢 Green text = Cross-sheet references

Sheet Q1 — Inputs
A1: Q1 — ROOTER SHOP: INPUT PARAMETERS
A3: GIVEN DATA (from assignment)
A4: Monthly Active Users (MAU) | B4: 1000000 | D4: As stated in assignment
A5: Avg Orders per User per Month | B5: 1.6 | D5: Given baseline frequency
A6: Average Order Value (AOV) | B6: 1500 | D6: Given baseline ticket size
A7: Gross Margin % | B7: 0.05 | D7: Given — very thin margin
A8: Net Profit % | B8: 0.03 | D8: Given
A10: LEVER 1 ASSUMPTIONS — Increase Purchase Frequency
A11: Target Frequency Increase | B11: 0.2 | D11: WHY: Digital goods (gift cards/gaming currency) have natural repeat-buy cycles. 20% lift (1.6→1.92 orders/month) is conservative for a targeted email + push campaign over 2-3 months. Comparable campaigns in D2C gaming show 15–25% lifts.
A12: Campaign Cost (monthly) | B12: 500000 | D12: WHY: Includes push notifications, email automation, and retargeting ads. ₹5L/month is lean for 10L MAU — roughly ₹0.50/user, typical for performance marketing in gaming.
A13: User Segment Targeted (%) | B13: 0.3 | D13: WHY: Targeting only 30% (lapsed/mid-frequency users) to avoid over-communication. Focusing on users with 1-2 orders/month who have headroom to buy more.
A15: LEVER 2 ASSUMPTIONS — Increase AOV
A16: Target AOV Increase | B16: 0.15 | D16: WHY: Bundle pricing (e.g., ₹500 UC + ₹300 gift card combo) and cross-sell prompts. 15% lift (₹1500→₹1725) is achievable via UI nudges. Higher denominations (₹2K, ₹5K packs) anchor the upsell.
A17: Campaign Cost (monthly) | B17: 300000 | D17: WHY: Primarily a UI/product change (bundle page, upsell widget) — lower execution cost than acquisition. One-time dev + A/B test infra ≈ ₹2-3L, ongoing ≈ ₹1L/month.
A18: Conversion Rate of Upsell | B18: 0.1 | D18: WHY: Only 10% of users shown a bundle will upgrade. Conservative — industry average for checkout upsell is 8-15%. This assumption is the stress-test candidate.

Sheet Q1 — BaseCase
A1: Q1 PART A — BASE CASE P&L (BEFORE ANY LEVER)
A3: Metric | B3: Monthly | C3: Annual
A4: MAU | B4: ='Q1 — Inputs'!B4 -> 1000000
A5: Avg Orders / User / Month | B5: ='Q1 — Inputs'!B5 -> 1.6
A6: Average Order Value (AOV) | B6: ='Q1 — Inputs'!B6 -> 1500
A7: ─── VOLUME ───
A8: Total Orders | B8: =B4*B5 -> 1600000 | C8: =B8*12 -> 19200000
A9: Total Revenue | B9: =B8*B6 -> 2400000000 | C9: =B9*12 -> 28800000000
A10: ─── PROFITABILITY ───
A11: Gross Profit | B11: =B9*'Q1 — Inputs'!B7 -> 120000000 | C11: =C9*'Q1 — Inputs'!B7 -> 1440000000
A12: Net Profit | B12: =B9*'Q1 — Inputs'!B8 -> 72000000 | C12: =C9*'Q1 — Inputs'!B8 -> 864000000
A15: Key Insight: At 5% GM, every ₹1 of revenue generates ₹0.05 gross profit. Incremental levers must overcome campaign costs to deliver net positive impact.
A16: Net Profit at 3% → ₹0.03 per ₹1 revenue. Margin is thin — volume + efficiency are the only real levers here.

Sheet Q1 — Scenarios
A1: Q1 PARTS A + B — LEVER COMPARISON: FREQUENCY vs AOV
A3: Metric | B3: Base Case | C3: Lever 1: Frequency ↑ | D3: Lever 2: AOV ↑ | E3: Winner?
A4: MAU | B4: ='Q1 — BaseCase'!B4 -> 1000000 | C4: ='Q1 — BaseCase'!B4 -> 1000000 | D4: ='Q1 — BaseCase'!B4 -> 1000000
A5: Avg Orders/User/Month | B5: ='Q1 — Inputs'!B5 -> 1.6 | C5: ='Q1 — Inputs'!B5*(1+'Q1 — Inputs'!B11) -> 1.92 | D5: ='Q1 — Inputs'!B5 -> 1.6
A6: AOV (₹) | B6: ='Q1 — Inputs'!B6 -> 1500 | C6: ='Q1 — Inputs'!B6 -> 1500 | D6: ='Q1 — Inputs'!B6*(1+'Q1 — Inputs'!B16) -> 1725
A7: Total Orders | B7: =B4*B5 -> 1600000 | C7: =C4*C5 -> 1920000 | D7: =D4*D5 -> 1600000
A8: Total Revenue (₹) | B8: =B7*B6 -> 2400000000 | C8: =C7*C6 -> 2880000000 | D8: =D7*D6 -> 2760000000
A9: Gross Profit (₹) | B9: =B8*'Q1 — Inputs'!B7 -> 120000000 | C9: =C8*'Q1 — Inputs'!B7 -> 144000000 | D9: =D8*'Q1 — Inputs'!B7 -> 138000000
A10: Campaign Cost (₹/month) | B10: 0 | C10: ='Q1 — Inputs'!B12 -> 500000 | D10: ='Q1 — Inputs'!B17 -> 300000
A11: Net Profit BEFORE Campaign (₹) | B11: =B8*'Q1 — Inputs'!B8 -> 72000000 | C11: =C8*'Q1 — Inputs'!B8 -> 86400000 | D11: =D8*'Q1 — Inputs'!B8 -> 82800000
A12: Net Profit AFTER Campaign (₹) | B12: =B11 -> 72000000 | C12: =C11-C10 -> 85900000 | D12: =D11-D10 -> 82500000
A13: Incremental Net Profit vs Base (₹) | B13: — | C13: =C12-B12 -> 13900000 | D13: =D12-B12 -> 10500000 | E13: =IF(C13>D13,"Lever 1 ✓",IF(D13>C13,"Lever 2 ✓","Tie")) -> Lever 1 ✓
A14: ROI on Campaign | B14: — | C14: =IF(C10>0,(C13/C10),"N/A") -> 27.8 | D14: =IF(D10>0,(D13/D10),"N/A") -> 35 | E14: =IF(C14>D14,"Lever 1 ✓",IF(D14>C14,"Lever 2 ✓","Tie")) -> Lever 2 ✓
A17: PART B — STRATEGIC RECOMMENDATION
A18: Recommended Lever: | B18: Lever 2 — AOV Increase | C18: WHY: Lower campaign cost (₹3L vs ₹5L), no reliance on behavioural change in short 2-3 month window. Digital goods have natural upsell path (₹500→₹1000 UC, bundle packs). Product-led change (UI/UX) vs. acquisition-heavy frequency play.
A19: Nature of Product: | B19: Digital gift cards / gaming currency | C19: One-time purchases with low emotional stickiness. Hard to force frequency. But upsell within an active session (when user intent is high) is naturally effective.
A20: 2-3 Month Window: | B20: Favors AOV lever | C20: Frequency change requires habit formation (60-90 days minimum). AOV lever activates the moment UI changes go live — faster payback.
A21: Risk: | B21: Upsell conversion rate | C21: If <5% users upgrade (vs assumed 10%), ROI flips negative. Validate via A/B test first (see StressTest sheet).

Sheet Q1 — StressTest
A1: Q1 PART C — STRESS TEST: Critical Assumption Analysis
A3: CRITICAL ASSUMPTION: Upsell Conversion Rate (currently assumed = 10%)
A4: If this assumption is wrong — i.e., users don't upgrade to larger bundles — Lever 2's incremental profit collapses, and the campaign cost becomes a pure loss.
A6: Upsell Conv. Rate | B6: AOV Achieved (₹) | C6: Total Revenue (₹) | D6: Net Profit After Campaign (₹) | E6: Incremental vs Base (₹) | F6: Verdict
A7: 0.03 | B7: =IF(A7>='Q1 — Inputs'!B18,'Q1 — Inputs'!B6*(1+'Q1 — Inputs'!B16),'Q1 — Inputs'!B6*(1+'Q1 — Inputs'!B16*(A7/'Q1 — Inputs'!B18))) -> 1567.5 | C7: ='Q1 — BaseCase'!B8*B7 -> 2508000000 | D7: =C7*'Q1 — Inputs'!B8-'Q1 — Inputs'!B17 -> 74940000 | E7: =D7-'Q1 — BaseCase'!B12 -> 2940000 | F7: =IF(E7<0,"❌ Loss",IF(E7<500000,"⚠️ Marginal","✅ Proceed")) -> ✅ Proceed
A8: 0.05 | B8: =IF(A8>='Q1 — Inputs'!B18,'Q1 — Inputs'!B6*(1+'Q1 — Inputs'!B16),'Q1 — Inputs'!B6*(1+'Q1 — Inputs'!B16*(A8/'Q1 — Inputs'!B18))) -> 1612.5 | C8: ='Q1 — BaseCase'!B8*B8 -> 2580000000 | D8: =C8*'Q1 — Inputs'!B8-'Q1 — Inputs'!B17 -> 77100000 | E8: =D8-'Q1 — BaseCase'!B12 -> 5100000 | F8: =IF(E8<0,"❌ Loss",IF(E8<500000,"⚠️ Marginal","✅ Proceed")) -> ✅ Proceed
A9: 0.08 | B9: =IF(A9>='Q1 — Inputs'!B18,'Q1 — Inputs'!B6*(1+'Q1 — Inputs'!B16),'Q1 — Inputs'!B6*(1+'Q1 — Inputs'!B16*(A9/'Q1 — Inputs'!B18))) -> 1680 | C9: ='Q1 — BaseCase'!B8*B9 -> 2688000000 | D9: =C9*'Q1 — Inputs'!B8-'Q1 — Inputs'!B17 -> 80340000 | E9: =D9-'Q1 — BaseCase'!B12 -> 8340000 | F9: =IF(E9<0,"❌ Loss",IF(E9<500000,"⚠️ Marginal","✅ Proceed")) -> ✅ Proceed
A10: 0.1 | B10: =IF(A10>='Q1 — Inputs'!B18,'Q1 — Inputs'!B6*(1+'Q1 — Inputs'!B16),'Q1 — Inputs'!B6*(1+'Q1 — Inputs'!B16*(A10/'Q1 — Inputs'!B18))) -> 1725 | C10: ='Q1 — BaseCase'!B8*B10 -> 2760000000 | D10: =C10*'Q1 — Inputs'!B8-'Q1 — Inputs'!B17 -> 82500000 | E10: =D10-'Q1 — BaseCase'!B12 -> 10500000 | F10: =IF(E10<0,"❌ Loss",IF(E10<500000,"⚠️ Marginal","✅ Proceed")) -> ✅ Proceed
A11: 0.12 | B11: =IF(A11>='Q1 — Inputs'!B18,'Q1 — Inputs'!B6*(1+'Q1 — Inputs'!B16),'Q1 — Inputs'!B6*(1+'Q1 — Inputs'!B16*(A11/'Q1 — Inputs'!B18))) -> 1725 | C11: ='Q1 — BaseCase'!B8*B11 -> 2760000000 | D11: =C11*'Q1 — Inputs'!B8-'Q1 — Inputs'!B17 -> 82500000 | E11: =D11-'Q1 — BaseCase'!B12 -> 10500000 | F11: =IF(E11<0,"❌ Loss",IF(E11<500000,"⚠️ Marginal","✅ Proceed")) -> ✅ Proceed
A12: 0.15 | B12: =IF(A12>='Q1 — Inputs'!B18,'Q1 — Inputs'!B6*(1+'Q1 — Inputs'!B16),'Q1 — Inputs'!B6*(1+'Q1 — Inputs'!B16*(A12/'Q1 — Inputs'!B18))) -> 1725 | C12: ='Q1 — BaseCase'!B8*B12 -> 2760000000 | D12: =C12*'Q1 — Inputs'!B8-'Q1 — Inputs'!B17 -> 82500000 | E12: =D12-'Q1 — BaseCase'!B12 -> 10500000 | F12: =IF(E12<0,"❌ Loss",IF(E12<500000,"⚠️ Marginal","✅ Proceed")) -> ✅ Proceed
A13: 0.2 | B13: =IF(A13>='Q1 — Inputs'!B18,'Q1 — Inputs'!B6*(1+'Q1 — Inputs'!B16),'Q1 — Inputs'!B6*(1+'Q1 — Inputs'!B16*(A13/'Q1 — Inputs'!B18))) -> 1725 | C13: ='Q1 — BaseCase'!B8*B13 -> 2760000000 | D13: =C13*'Q1 — Inputs'!B8-'Q1 — Inputs'!B17 -> 82500000 | E13: =D13-'Q1 — BaseCase'!B12 -> 10500000 | F13: =IF(E13<0,"❌ Loss",IF(E13<500000,"⚠️ Marginal","✅ Proceed")) -> ✅ Proceed
A16: HOW TO VALIDATE BEFORE COMMITTING RESOURCES
A17: Step 1 — A/B Test | B17: Run a 2-week A/B test with 5% of users. Show bundle/upsell to Group A, default to Group B. Measure actual conversion rate.
A18: Step 2 — Cohort Analysis | B18: Check historical data: do users who buy ₹1000+ packs already exist? What % of current orders are already at higher AOV? Reveals natural ceiling.
A19: Step 3 — Break-even Calc | B19: From this table: break-even is at ~5-6% conversion. If A/B test shows >6%, proceed. If <6%, pivot to Lever 1 or hybrid approach.
A20: Step 4 — Timing | B20: A/B test takes 2 weeks → decision by end of Week 2 → 6 weeks left in 2-month window for full rollout. Timing is tight but viable.

Sheet Q2 — Inputs
A1: Q2 — BGMI TOURNAMENT: INPUT PARAMETERS
A3: GIVEN DATA
A4: Total Weekly Participants | B4: 100000 | D4: Given
A5: Current Winners Rewarded | B5: 100 | D5: Top 100 only
A6: Weekly Reward Budget (₹) | B6: 50000 | D6: Given — fixed constraint
A7: Current Budget/User (₹) | B7: =B6/B4 -> 0.5 | D7: ₹0.50 per user — insufficient for pure monetary
A8: % Users NOT winning | B8: =(B4-B5)/B4 -> 0.999 | D8: 99.9% feel unrewarded every week
A10: SEGMENT ASSUMPTIONS (Part B)
A11: Tier 1 — Top 100 (Elite Winners) | B11: 100 | D11: Given — unchanged from current format
A12: Tier 2 — Top 101–1000 (Near-Winners) | B12: 900 | D12: Top 1% minus elite — strong performers, high frustration if ignored
A13: Tier 3 — Top 1001–10000 (Aspirational) | B13: 9000 | D13: Top 10% — growing players with realistic path to Tier 2
A14: Tier 4 — Top 10001–50000 (Participators) | B14: 40000 | D14: Middle bulk — need encouragement, not competition
A15: Tier 5 — Bottom 50001–100000 (Casual) | B15: 50000 | D15: High churn risk — fun-seekers, need non-monetary hooks
A16: Segment Total Check | B16: =SUM(B11:B15) -> 100000 | D16: Must equal B4 (100,000) — validation check
A17: BUDGET ALLOCATION ASSUMPTIONS (Part B)
A18: Tier 1 — Elite Budget Allocation % | B18: 0.6 | D18: 60% to Top 100: maintains competitive integrity, each gets ₹300
A19: Tier 2 — Near-Winner Allocation % | B19: 0.2 | D19: 20% to Top 101-1000: ₹11.1 each — enough to feel recognised
A20: Tier 3 — Aspirational Allocation % | B20: 0.12 | D20: 12% to next 9000: ₹6.7 each — small but tangible
A21: Tier 4 — Participator Allocation % | B21: 0.05 | D21: 5% to 40K users: ₹6.25 each — nominal, primary reward is non-monetary
A22: Tier 5 — Casual Allocation % | B22: 0.03 | D22: 3% to 50K users: ₹3 each — symbolic, non-monetary is the real reward
A23: Budget Alloc Check (must = 100%) | B23: =SUM(B18:B22) -> 1 | D23: Must equal 100% — validation check

Sheet Q2 — Diagnosis
A1: Q2 PART A — NEGATIVE FEEDBACK LOOP: DIAGNOSIS
A3: THE FEEDBACK LOOP — STEP BY STEP
A4: Step 1 — Low Win Probability | B4: Win probability = 100/100,000 = 0.001%. Vroom's Expectancy Theory: Motivation = Expectancy × Instrumentality × Valence. When Expectancy ≈ 0, motivation collapses regardless of reward size.
A5: Step 2 — Effort Feels Futile | B5: Player spends 20-30 min on their match, submits scorecard, sees rank #4,521. No reward, no acknowledgement. Seligman's Learned Helplessness: repeated failure with no perceived control leads to psychological disengagement.
A6: Step 3 — Negative Emotion Dominates | B6: Core emotion: SHAME + HUMILIATION (not just disappointment). Being ranked publicly against 99,999 others and failing creates social comparison anxiety — especially in competitive gaming culture.
A7: Step 4 — Zero Progress Markers | B7: Current system has no intermediate milestone. User sees the same 0 reward week after week. No sense of improvement, no 'closing the gap' signal. Progress Theory (Teresa Amabile): small wins drive engagement — current format has none.
A8: Step 5 — Churn Decision | B8: After 2-3 failed weeks, user concludes: 'This game/tournament is not for me.' Cognitive dissonance resolved by quitting rather than re-evaluating skill. Weekly retention drops.
A9: Step 6 — The Loop Reinforces | B9: As casual users quit, leaderboard becomes increasingly dominated by pros. Win probability for remaining users drops further. Loop accelerates.
A11: FRAMEWORKS USED
A12: Seligman's Learned Helplessness (1967) | B12: Repeated uncontrollable failure → user stops trying. Applied: 99,900 users lose every week with no control over outcome → disengage.
A13: Vroom's Expectancy Theory (1964) | B13: Motivation = E × I × V. Win prob 0.001% → E=0 → Total motivation = 0. Even ₹50K prize can't fix near-zero expectancy.
A14: Amabile's Progress Principle (2011) | B14: Perception of making progress is the #1 driver of engagement. Current format shows zero progress for 99,900 users.
A15: Self-Determination Theory (Deci & Ryan) | B15: Users need Autonomy, Competence, Relatedness. Current format attacks all three: no control, no skill recognition, no community signal.

Sheet Q2 — RewardFramework
A1: Q2 PART B — 5-TIER REWARD FRAMEWORK (₹50,000 Budget)
A3: Tier | B3: Users | C3: Budget Alloc % | D3: Budget (₹) | E3: Per-User Reward (₹) | F3: What They Receive | G3: Behavior Reinforced
A4: T1: Elite (Rank 1–100) | B4: ='Q2 — Inputs'!B11 -> 100 | C4: ='Q2 — Inputs'!B18 -> 0.6 | D4: =C4*'Q2 — Inputs'!B6 -> 30000 | E4: =IF(B4>0,D4/B4,0) -> 300 | F4: ₹300 cash + 'BGMI Champion' verified badge + Rooter Pro subscription (1 month) + Permanent leaderboard hall of fame entry | G4: Competitive excellence, public status, repeat participation to defend title
A5: T2: Near-Winner (Rank 101–1000) | B5: ='Q2 — Inputs'!B12 -> 900 | C5: ='Q2 — Inputs'!B19 -> 0.2 | D5: =C5*'Q2 — Inputs'!B6 -> 10000 | E5: =IF(B5>0,D5/B5,0) -> 11.111111 | F5: ₹11 cash + 'Top 1%' digital rank card (shareable to WhatsApp/Instagram) + Priority registration slot for next week | G5: Aspiration to reach T1, reduces frustration of 'almost winning', creates weekly habit
A6: T3: Aspirational (Rank 1001–10000) | B6: ='Q2 — Inputs'!B13 -> 9000 | C6: ='Q2 — Inputs'!B20 -> 0.12 | D6: =C6*'Q2 — Inputs'!B6 -> 6000 | E6: =IF(B6>0,D6/B6,0) -> 0.66666667 | F6: ₹6.7 cash + Personalised 'Tournament DNA' report (AI-generated: your best weapon, kill trend, improvement score) + 'Top 10%' badge | G6: Progress visibility, skill growth signal, identity as 'improving player'
A7: T4: Participator (Rank 10001–50000) | B7: ='Q2 — Inputs'!B14 -> 40000 | C7: ='Q2 — Inputs'!B21 -> 0.05 | D7: =C7*'Q2 — Inputs'!B6 -> 2500 | E7: =IF(B7>0,D7/B7,0) -> 0.0625 | F7: ₹6.25 Rooter coins (redeemable in store) + Friends Mini-League invitation (compete only vs your squad) + Weekly streak badge | G7: Community belonging, reduced social comparison anxiety, streak maintenance
A8: T5: Casual (Rank 50001–100000) | B8: ='Q2 — Inputs'!B15 -> 50000 | C8: ='Q2 — Inputs'!B22 -> 0.03 | D8: =C8*'Q2 — Inputs'!B6 -> 1500 | E8: =IF(B8>0,D8/B8,0) -> 0.03 | F8: ₹3 scratch-card (gamified reveal of small discount/coin) + 'Participation Streak' counter + 'You ranked higher than X players!' message | G8: Fun over competition, loss aversion (streak break), relative rank positivity
A9: TOTAL | B9: =SUM(B4:B8) -> 100000 | C9: =SUM(C4:C8) -> 1 | D9: =SUM(D4:D8) -> 50000

Sheet Q2 — NonMonetary
A1: Q2 PART C — NON-MONETARY REWARD MECHANISMS (₹0 Budget)
A3: Mechanism | B3: How It Works | C3: Psychology Exploited | D3: Target Tier
A4: Tournament DNA Report | B4: After each week, every player (Tier 3+) gets an AI-generated 1-page report: 'Your best weapon this week was M416. Your kill consistency improved 12% vs last week. You rank in the top 23% for damage per match.' Generated automatically from OCR scorecard data. | C4: Progress Principle (Amabile): Seeing quantified improvement creates intrinsic motivation even without a prize. Identity-based — player becomes 'the one who's getting better'. | D4: T3, T4
A5: Shareable Rank Identity Card | B5: Auto-generated image card: 'I ranked Top 2% in Rooter BGMI Week 34 🎯'. Styled like a stats card. One-tap share to Instagram Stories, WhatsApp. Card shows kill stats, accuracy, improvement badge. | C5: Social Identity Theory: Public performance identity drives return visits. Social proof loop — friends see the card, discover the tournament. Zero cost, viral acquisition channel. | D5: T2, T3
A6: Friends Mini-League | B6: Every user can create a private group of up to 10 friends. Mini-leaderboard only within that group. Win probability = 1/10, not 1/100,000. Weekly winner gets a 'Squad King' title on their profile. | C6: Reduces social comparison anxiety. Autonomy (you choose your competition set). 10x higher win probability restores Expectancy in Vroom's model. Relatedness need met. | D6: T4, T5
A7: Streak Counter + Loss Aversion Hook | B7: 'You've played 4 weeks in a row. Miss next week and your streak resets.' Shown prominently in app. After 3 weeks, streak frame appears on profile avatar. | C7: Loss Aversion (Kahneman): Fear of losing a streak is stronger than desire to gain. Streaks cost nothing but drive weekly return visits. Duolingo's core retention mechanic. | D7: T4, T5
A8: Skill Milestone Badges (Non-Generic) | B8: Not generic badges. Specific unlocks: 'Sniper Specialist' (top 10% accuracy with bolt-action rifles for 3 consecutive weeks), 'Clutch King' (3+ solo-squad kills in a single match, verified by OCR). Each badge shows exact achievement. | C8: Competence need (Self-Determination Theory). Specific badges create concrete goals. Players actively try to hit the badge criteria — drives engagement quality, not just quantity. | D8: T3, T4
A9: 'You Beat X Players' Relative Rank Message | B9: Instead of showing absolute rank (#47,832), show: 'You outperformed 52,168 players this week — that's more than last week!' Reframes failure as relative success. | C9: Positive reframing reduces shame response. Directional progress signal even for bottom-half users. Small but measurable — cost: one UX copy change. | D9: T5
A10: Pro League Promotion Pathway | B10: Visible on-screen: 'Rank Top 1000 for 3 consecutive weeks → Auto-qualify for Rooter Pro League (higher prizes).' Tier 3 users have a visible 3-week path to Tier 2 status. | C10: Goal Gradient Effect: As users approach a milestone, effort accelerates. Visible pathway converts Tier 3 from 'passive participants' to 'active aspirants'. | D10: T3

Sheet Q2 — StressTest
A1: Q2 PART D — STRESS TEST: Same Winners Repeat Every Week
A3: PSYCHOLOGICAL IMPACT ON 99,900 USERS
A4: Week | B4: Event | C4: Psychological Impact on 99,900
A5: Week 1 | B5: Same 100 winners emerge | C5: Mild frustration — users assume it's luck, will try again
A6: Week 2 | B6: Same 100 win again | C6: Pattern recognition begins. 'These are pros.' Expectancy drops. T2-T3 users feel the 'gap' is structural.
A7: Week 3 | B7: Same 100 win for 3rd time | C7: Learned Helplessness fully activated. 'I can never win this.' T4-T5 users stop competing seriously. Participation numbers up but engagement quality drops.
A8: Week 4 | B8: Same 100 confirmed dominant | C8: Social proof reversal: the DNA Reports and rank cards feel hollow. 'What's the point of being Top 15% if the same 100 pros always win?' Framework's non-monetary layer loses credibility.
A10: DOES THE FRAMEWORK SURVIVE?
A11: Partial Survival — Lower tiers (T4, T5) survive via non-monetary hooks (streaks, mini-leagues, DNA reports). But T2-T3 framework fails: near-winners who never breakthrough will disengage despite rank cards.
A13: 3 STRUCTURAL FIXES
A14: Fix 1 — Skill Brackets | B14: Create 3 parallel brackets: Bronze (new users, <10 games), Silver (11-50 games), Gold (50+ games). Each bracket has its own Top 100. A Bronze player can be a champion in their bracket. Win probability becomes 100/33,000 per bracket — 3x higher than before.
A15: Fix 2 — Weekly Wildcard Slot | B15: Reserve 1 spot in Top 100 rewards for a randomly selected user from Rank 101-10,000 who showed the highest improvement week-over-week. This creates a 'luck + merit' pathway. Even a Rank 500 player can dream of the wildcard. Pure lottery psychology.
A16: Fix 3 — Pro League Separation | B16: After Week 4, any user who wins Top 100 twice enters 'Rooter Pro League' — a separate track with different rewards. Main tournament clears automatically. Fresh competition every month. Top 100 is no longer dominated by the same players.

Sheet AI Prompt Log
A1: AI USAGE DISCLOSURE — Prompts + Tools Used
A3: # | B3: Tool / Model | C3: Task | D3: Prompt Used | E3: Output Generated
A4: 1 | B4: Claude (Anthropic) Claude Sonnet 4 | C4: Q1 — Growth Lever Analysis | D4: You are a growth analyst at Rooter Shop. The business has: MAU 1M, Avg Orders/User 1.6, AOV ₹1500, GM 5%, Net Profit 3%. Leadership wants to grow via (A) increasing frequency or (B) increasing AOV over 2-3 months. Build a profit impact model for both levers. State all assumptions and justify why. Then recommend one lever based on product category and time window. Finally, identify the single most critical assumption and how to validate it before committing budget. | E4: Q1 Parts A, B, C — full analysis, lever comparison, stress test, break-even framework used in Sheets Q1—Inputs, Q1—BaseCase, Q1—Scenarios, Q1—StressTest
A5: 2 | B5: Claude (Anthropic) Claude Sonnet 4 | C5: Q2 — BGMI Tournament Diagnosis | D5: You are a product analyst at a gaming startup. 1,00,000 users participate in a weekly BGMI tournament. Only Top 100 win rewards. Weekly retention is dropping. Explain exactly why the current format creates a negative feedback loop using behavioral psychology frameworks. What is the core emotion driving churn? Apply Seligman's Learned Helplessness, Vroom's Expectancy Theory, and Amabile's Progress Principle. | E5: Q2 Part A — Diagnosis framework, 6-step loop, 4 psychological frameworks used in Q2—Diagnosis sheet
A6: 3 | B6: Claude (Anthropic) Claude Sonnet 4 | C6: Q2 — Reward Framework Design | D6: Design a 5-tier reward framework for 1,00,000 BGMI tournament users with a budget of ₹50,000/week. Segment users into tiers by rank, state what each tier receives (monetary + non-monetary), justify the budget split, and explain what behavior each reward is designed to reinforce. The framework must maintain Top 100 competitive integrity while maximising the number of users who feel rewarded. | E6: Q2 Part B — 5-tier segmentation, budget allocation percentages, reward descriptions used in Q2—Inputs and Q2—RewardFramework sheets
A7: 4 | B7: Claude (Anthropic) Claude Sonnet 4 | C7: Q2 — Non-Monetary Mechanisms | D7: ₹50,000 across 1,00,000 users = ₹0.50/user. Design non-monetary reward mechanisms that make users feel rewarded without any budget. Be highly specific — no generic badge lists. Each mechanism must name the psychological principle it exploits, which user tier it targets, and exactly how it works in the product. | E7: Q2 Part C — 7 specific non-monetary mechanisms with psychology used in Q2—NonMonetary sheet
A8: 5 | B8: Claude (Anthropic) Claude Sonnet 4 | C8: Q2 — Stress Test (Same Winners) | D8: Your BGMI tournament framework is live for 4 weeks. The same 100 users win every week. Walk through the psychological impact on the 99,900 users week by week. Does the framework survive? If not, provide 3 structural fixes that prevent the same-winner lock-in problem. | E8: Q2 Part D — Week-by-week psychological impact, framework survivability verdict, 3 structural fixes used in Q2—StressTest sheet
A9: 6 | B9: Claude (Anthropic) Claude Sonnet 4 | C9: Excel Model Construction | D9: Build a professional multi-sheet Excel model combining Q1 and Q2 analysis. Use industry-standard color coding (blue=inputs, black=formulas, green=cross-sheet, yellow=assumptions). Zero formula errors. Include: Index sheet, Q1 Inputs/BaseCase/Scenarios/StressTest, Q2 Inputs/Diagnosis/RewardFramework/NonMonetary/StressTest, AI Prompt Log. All sheets must reference a central inputs sheet for dynamic recalculation. | E9: Full Excel workbook architecture — 11 sheets, cross-sheet formula references, color-coded model
A12: AI Usage Policy: All AI usage is disclosed above. Claude (Anthropic) was used as a reasoning and analysis partner. All assumptions, frameworks, and numbers were validated by the analyst before inclusion. The model architecture, formula design, and business judgment are the analyst's own.
